lazyds/__init__.py
lazyds/data/__init__.py
lazyds/data/dataset.py
lazyds/data/manipulation.py
lazyds/evaluation/__init__.py
lazyds/evaluation/split.py
lazyds/learning/__init__.py
lazyds/learning/supervised/__init__.py
lazyds/learning/supervised/classification/__init__.py
lazyds/learning/supervised/classification/rf.py
lazyds-0.211124.4.dist-info/LICENSE
lazyds-0.211124.4.dist-info/WHEEL
lazyds-0.211124.4.dist-info/METADATA
lazyds-0.211124.4.dist-info/RECORD
